recommender_system/__init__.py
recommender_system-0.0.1.dist-info/METADATA
recommender_system-0.0.1.dist-info/RECORD
recommender_system-0.0.1.dist-info/WHEEL
recommender_system-0.0.1.dist-info/top_level.txt
