Metadata-Version: 2.1
Name: recommender-system
Version: 0.0.1
Summary: Acuracy and Efficient Recommander System
Home-page: https://github.com/itengying/
Author: Bei Zhou
Author-email: best.recommender.system@gmail.com
License: UNKNOWN
Platform: UNKNOWN
Classifier: Programming Language :: Python :: 3
Classifier: License :: OSI Approved :: MIT License
Classifier: Operating System :: OS Independent
